visceral/__init__.py 
visceral/app.py
visceral/cmd.txt
visceral/mcp_server.py
visceral/request_bid.py
visceral/survey.py
visceral/survey_data.xlsx
visceral/American_Directions/ai_chat.py
visceral/American_Directions/annotation.py
visceral/American_Directions/ask_if.py
visceral/American_Directions/categorizer.py
visceral/American_Directions/categorizer_v2.py
visceral/American_Directions/clean_json.py
visceral/American_Directions/contact_form.py
visceral/American_Directions/currency.py
visceral/American_Directions/grid.py
visceral/American_Directions/hidden_variable.py
visceral/American_Directions/maxdiff.py
visceral/American_Directions/multi_percentage.py
visceral/American_Directions/multi_select.py
visceral/American_Directions/multi_select_grid.py
visceral/American_Directions/multi_text.py
visceral/American_Directions/notes.py
visceral/American_Directions/nps.py
visceral/American_Directions/number.py
visceral/American_Directions/number_of_question.py
visceral/American_Directions/percent_sum.py
visceral/American_Directions/percentage.py
visceral/American_Directions/phone.py
visceral/American_Directions/process_complex_text.py
visceral/American_Directions/ranking.py
visceral/American_Directions/single_select.py
visceral/American_Directions/single_text.py
visceral/American_Directions/split_questions.py
visceral/American_Directions/sync.py
visceral/American_Directions/terminate.py
visceral/American_Directions/transition.py
visceral/American_Directions/unknown.py
visceral/American_Directions/van_westendorp.py
visceral/American_Directions/year.py
visceral/American_Directions/zip_code.py
visceral/CreateSection/Functions/annotation.py
visceral/CreateSection/Functions/extract_survey_questions.py
visceral/CreateSection/Functions/generate_uuid.py
visceral/CreateSection/Functions/get_block_names.py
visceral/CreateSection/Functions/helper.py
visceral/CreateSection/Functions/identify_questions.py
visceral/CreateSection/Functions/image.py
visceral-0.1.2.dist-info/METADATA
visceral-0.1.2.dist-info/WHEEL
visceral-0.1.2.dist-info/entry_points.txt
visceral-0.1.2.dist-info/RECORD
