Metadata-Version: 2.4
Name: visceral
Version: 0.1.2
Summary: MCP server for Visceral survey and workspace management
Author-email: Anshuman <anshuman@visceral.ai>
Keywords: mcp,research,survey,visceral,workspace
Requires-Python: >=3.9
Requires-Dist: mcp==1.9.2
Requires-Dist: python-dotenv==1.1.0
Requires-Dist: requests==2.32.3
Requires-Dist: websockets==15.0.1
